{
    "Type":"Documentation",
    "Technology":"MPI",
    "Name":"MPI_ORDER_C",
    "DirectoryName":"mpi_order_c",
    "SharedDescription":true,
    "Description":"MPI_ORDER_C indicates that the memory storage order to apply in that of C; row-major order. That is, consecutive elements in memory are that of the rightmost dimension in arrays. It is used for instance in routines like MPI_Type_create_subarray and MPI_Type_create_darray. The other memory storage order is MPI_ORDER_FORTRAN.",
    "Categories":[
        "User datatypes"
    ],
    "Languages": [
        {
            "Language":"C"
        }
    ]
}